rust_fst-0.1.2.data/purelib/rust_fst/__init__.py
rust_fst-0.1.2.data/purelib/rust_fst/_build_ffi.py
rust_fst-0.1.2.data/purelib/rust_fst/_ffi.py
rust_fst-0.1.2.data/purelib/rust_fst/common.py
rust_fst-0.1.2.data/purelib/rust_fst/lib.py
rust_fst-0.1.2.data/purelib/rust_fst/libfstwrapper.dylib
rust_fst-0.1.2.data/purelib/rust_fst/map.py
rust_fst-0.1.2.data/purelib/rust_fst/set.py
rust_fst-0.1.2.dist-info/DESCRIPTION.rst
rust_fst-0.1.2.dist-info/METADATA
rust_fst-0.1.2.dist-info/RECORD
rust_fst-0.1.2.dist-info/WHEEL
rust_fst-0.1.2.dist-info/metadata.json
rust_fst-0.1.2.dist-info/top_level.txt
