Metadata-Version: 2.0
Name: rust-fst
Version: 0.1.2
Summary: Python bindings for the Rust `fst` create, providing sets and maps backed by finite state transducers.
Home-page: https://github.com/jbaiter/python-rust-fst
Author: Johannes Baiter
Author-email: johannes.baiter@gmail.com
License: MIT
Keywords: fst,rust,levenshtein,automata,transducer,data_structures
Platform: UNKNOWN
Classifier: Development Status :: 4 - Beta
Classifier: Intended Audience :: Developers
Classifier: Intended Audience :: Science/Research
Classifier: License :: OSI Approved :: MIT License
Classifier: Topic :: Text Processing :: Indexing
Requires-Dist: cffi (>=1.0.0)
